semverit.py
semverit-0.4.2.dist-info/LICENSE
semverit-0.4.2.dist-info/METADATA
semverit-0.4.2.dist-info/WHEEL
semverit-0.4.2.dist-info/RECORD
