Metadata-Version: 2.3
Name: SemVerIt
Version: 0.4.2
Summary: Manipulate semantic versioning strings.
License: MIT
Author: Hendrik du Toit
Author-email: hendrik@brightedge.co.za
Requires-Python: >=3.10
Classifier: Development Status :: 4 - Beta
Classifier: Intended Audience :: Developers
Classifier: Intended Audience :: Information Technology
Classifier: Intended Audience :: System Administrators
Classifier: License :: OSI Approved :: MIT License
Classifier: Topic :: Software Development :: Version Control :: Git
Classifier: Topic :: System :: Archiving :: Packaging
Classifier: Programming Language :: Python :: 3.10
Classifier: Programming Language :: Python :: 3.11
Classifier: Programming Language :: Python :: 3.12
Requires-Dist: beetools (>=5.2.4,<6.0.0)
Project-URL: Homepage, https://github.com/BrightEdgeeServices/SemVerIt
Project-URL: Repository, https://github.com/BrightEdgeeServices/SemVerIt.git
Project-URL: changelog, https://github.com/BrightEdgeeServices/SemVerIt/blob/enhancement/master/ReleaseNotes.md
Project-URL: issues, https://github.com/BrightEdgeeServices/SemVerIt/issues
